Metadata-Version: 2.1
Name: pu-utils
Version: 0.0.9
Summary: Random stuff to help writing Pulumi scripts easier
License:                                  Apache License
Project-URL: Source, https://github.com/duongdominhchau/pulumi-utils
Requires-Python: >=3.12.0
Requires-Dist: pulumi
Requires-Dist: uv
Requires-Dist: pyright; extra == "dev"
Requires-Dist: ruff; extra == "dev"
Requires-Dist: ward; extra == "dev"
Requires-Dist: twine; extra == "dev"
Requires-Dist: build; extra == "dev"
Requires-Dist: pulumi-aws; extra == "aws"
Provides-Extra: dev
Provides-Extra: aws
